qixnat/__init__.py
qixnat/command.py
qixnat/config.py
qixnat/configuration.py
qixnat/connection.py
qixnat/facade.py
qixnat/helpers.py
qixnat/project.py
qixnat-2.1.3.data/scripts/qicp
qixnat-2.1.3.data/scripts/qils
qixnat-2.1.3.data/scripts/qirm
qixnat-2.1.3.dist-info/DESCRIPTION.rst
qixnat-2.1.3.dist-info/METADATA
qixnat-2.1.3.dist-info/metadata.json
qixnat-2.1.3.dist-info/RECORD
qixnat-2.1.3.dist-info/top_level.txt
qixnat-2.1.3.dist-info/WHEEL
