Metadata-Version: 2.0
Name: qixnat
Version: 2.1.3
Summary: XNAT facade.
Home-page: https://github.com/ohsu-qin/qixnat
Author: OHSU Knight Cancer Institute
Author-email: loneyf@ohsu.edu
License: MIT
Keywords: Imaging QIN XNAT
Platform: Any
Classifier: Development Status :: 5 - Production/Stable
Classifier: Topic :: Scientific/Engineering :: Bio-Informatics
Classifier: Environment :: Console
Classifier: Intended Audience :: Science/Research
Classifier: License :: OSI Approved :: MIT License
Classifier: Operating System :: OS Independent
Classifier: Programming Language :: Python
Classifier: Programming Language :: Python :: 2.6
Classifier: Programming Language :: Python :: 2.7
Requires-Dist: httplib2 (==0.9)
Requires-Dist: lxml (==3.4.0)
Requires-Dist: nose (==1.3.0)
Requires-Dist: pyxnat (==0.9.5.2)
Requires-Dist: Sphinx (==1.2.2)
Requires-Dist: qiutil (==2.1.4)
